# 字节码结构与常量池

## 概述

Java 字节码是 JVM 的"汇编语言"，是 Java 源码编译后的中间表示。class 文件采用精心设计的二进制格式，包含类型信息、字段、方法、常量池等所有运行时必需的数据。

理解字节码结构的关键：
- **常量池**：存储字面量、类型引用、方法引用
- **字节码指令**：基于栈的指令集
- **属性表**：泛型签名、异常表、行号表等元数据

本章聚焦 class 文件的结构解析与常量池机制。

---

## 1. class 文件的整体结构

### 魔数与版本号

**class 文件开头**：

```
CA FE BA BE 00 00 00 34
```

- `CA FE BA BE`：魔数（Magic Number），标识 class 文件格式
- `00 00`：次版本号（Minor Version）
- `00 34`：主版本号（Major Version），52 = Java 8

**版本号映射**：

| Java 版本 | 主版本号 | 十六进制 |
| --------- | -------- | -------- |
| Java 8    | 52       | 0x0034   |
| Java 11   | 55       | 0x0037   |
| Java 17   | 61       | 0x003D   |

### class 文件结构

```
ClassFile {
    u4             magic;                    // 魔数 0xCAFEBABE
    u2             minor_version;            // 次版本号
    u2             major_version;            // 主版本号
    u2             constant_pool_count;      // 常量池大小
    cp_info        constant_pool[...];       // 常量池
    u2             access_flags;             // 访问标志
    u2             this_class;               // 类索引
    u2             super_class;              // 父类索引
    u2             interfaces_count;         // 接口数量
    u2             interfaces[...];          // 接口表
    u2             fields_count;             // 字段数量
    field_info     fields[...];              // 字段表
    u2             methods_count;            // 方法数量
    method_info    methods[...];             // 方法表
    u2             attributes_count;         // 属性数量
    attribute_info attributes[...];          // 属性表
}
```

---

## 2. 常量池的结构与类型

### 常量池索引

**特殊规则**：

- 索引从 1 开始（0 保留）
- `constant_pool_count` 实际包含的常量是 `count - 1` 个
- long 和 double 占用两个索引位

### 常量类型

**14 种常量类型**：

| 类型                    | 标志 | 用途                     |
| ----------------------- | ---- | ------------------------ |
| CONSTANT_Utf8           | 1    | UTF-8 字符串             |
| CONSTANT_Integer        | 3    | int 字面量               |
| CONSTANT_Float          | 4    | float 字面量             |
| CONSTANT_Long           | 5    | long 字面量              |
| CONSTANT_Double         | 6    | double 字面量            |
| CONSTANT_Class          | 7    | 类或接口的符号引用       |
| CONSTANT_String         | 8    | String 字面量            |
| CONSTANT_Fieldref       | 9    | 字段的符号引用           |
| CONSTANT_Methodref      | 10   | 方法的符号引用           |
| CONSTANT_InterfaceMethodref | 11 | 接口方法的符号引用     |
| CONSTANT_NameAndType    | 12   | 名称和类型描述符         |
| CONSTANT_MethodHandle   | 15   | 方法句柄（Java 7+）      |
| CONSTANT_MethodType     | 16   | 方法类型（Java 7+）      |
| CONSTANT_InvokeDynamic  | 18   | invokedynamic 指令       |

### 常量池示例

**源码**：

```java
public class Demo {
    private String name = "Hello";
    
    public void print() {
        System.out.println(name);
    }
}
```

**常量池**（javap -v 输出）：

```
Constant pool:
   #1 = Methodref          #6.#20         // java/lang/Object."<init>":()V
   #2 = String             #21            // Hello
   #3 = Fieldref           #5.#22         // Demo.name:Ljava/lang/String;
   #4 = Fieldref           #23.#24        // java/lang/System.out:Ljava/io/PrintStream;
   #5 = Class              #25            // Demo
   #6 = Class              #26            // java/lang/Object
   #7 = Utf8               name
   #8 = Utf8               Ljava/lang/String;
   #9 = Utf8               <init>
  #10 = Utf8               ()V
  #11 = Utf8               Code
  #12 = Utf8               print
  #13 = Utf8               System
  #14 = Utf8               out
  #15 = Utf8               Ljava/io/PrintStream;
  ...
```

### 符号引用的组成

**Fieldref 结构**：

```
CONSTANT_Fieldref {
    u1 tag = 9;
    u2 class_index;        // 指向 CONSTANT_Class
    u2 name_and_type_index; // 指向 CONSTANT_NameAndType
}
```

**示例**：

```
#3 = Fieldref #5.#22
  ↓
#5 = Class #25          // Demo
#22 = NameAndType #7:#8 // name:Ljava/lang/String;
  ↓
#7 = Utf8 "name"
#8 = Utf8 "Ljava/lang/String;"
```

---

## 3. 字节码指令集

### 基于栈的指令集

**特点**：

- 操作数栈（Operand Stack）保存中间结果
- 指令简洁，操作数隐式在栈顶
- 平台无关，易于移植

**示例**：计算 `a + b`

**栈式虚拟机**（Java）：

```
iload_1    // 将局部变量 1 压栈
iload_2    // 将局部变量 2 压栈
iadd       // 弹出两个值，相加，结果压栈
istore_3   // 弹出结果，存入局部变量 3
```

**寄存器虚拟机**（Android Dalvik）：

```
add-int v3, v1, v2  // v3 = v1 + v2
```

### 指令分类

**1. 加载和存储指令**

```
iload_0   // 将局部变量 0 (int) 加载到栈
aload_1   // 将局部变量 1 (引用) 加载到栈
istore_2  // 弹出栈顶 int，存入局部变量 2
astore_3  // 弹出栈顶引用，存入局部变量 3
```

**2. 运算指令**

```
iadd      // int 加法
isub      // int 减法
imul      // int 乘法
idiv      // int 除法
irem      // int 取余
```

**3. 类型转换**

```
i2l       // int → long
i2f       // int → float
l2i       // long → int
checkcast // 引用类型强制转换
```

**4. 对象操作**

```
new           // 创建对象
newarray      // 创建基本类型数组
anewarray     // 创建引用类型数组
getfield      // 获取对象字段
putfield      // 设置对象字段
invokevirtual // 调用虚方法
invokespecial // 调用构造方法/私有方法/父类方法
invokestatic  // 调用静态方法
```

**5. 控制转移**

```
ifeq      // int 等于 0 则跳转
ifne      // int 不等于 0 则跳转
if_icmpeq // 两个 int 相等则跳转
goto      // 无条件跳转
```

### 字节码示例

**源码**：

```java
public int add(int a, int b) {
    return a + b;
}
```

**字节码**：

```
public int add(int, int);
  Code:
     0: iload_1       // 加载参数 a
     1: iload_2       // 加载参数 b
     2: iadd          // 执行加法
     3: ireturn       // 返回结果
```

---

## 4. 访问标志与描述符

### 访问标志（Access Flags）

**类的访问标志**：

| 标志名         | 值     | 含义           |
| -------------- | ------ | -------------- |
| ACC_PUBLIC     | 0x0001 | public         |
| ACC_FINAL      | 0x0010 | final          |
| ACC_SUPER      | 0x0020 | 使用新的 invokespecial |
| ACC_INTERFACE  | 0x0200 | 接口           |
| ACC_ABSTRACT   | 0x0400 | abstract       |
| ACC_SYNTHETIC  | 0x1000 | 编译器生成     |
| ACC_ANNOTATION | 0x2000 | 注解类型       |
| ACC_ENUM       | 0x4000 | 枚举类型       |

**方法的访问标志**：

| 标志名         | 值     | 含义           |
| -------------- | ------ | -------------- |
| ACC_PUBLIC     | 0x0001 | public         |
| ACC_PRIVATE    | 0x0002 | private        |
| ACC_PROTECTED  | 0x0004 | protected      |
| ACC_STATIC     | 0x0008 | static         |
| ACC_FINAL      | 0x0010 | final          |
| ACC_SYNCHRONIZED | 0x0020 | synchronized |
| ACC_BRIDGE     | 0x0040 | 桥方法         |
| ACC_VARARGS    | 0x0080 | 可变参数       |
| ACC_NATIVE     | 0x0100 | native         |
| ACC_ABSTRACT   | 0x0400 | abstract       |

### 类型描述符

**基本类型**：

| 字符 | 类型    |
| ---- | ------- |
| B    | byte    |
| C    | char    |
| D    | double  |
| F    | float   |
| I    | int     |
| J    | long    |
| S    | short   |
| Z    | boolean |
| V    | void    |

**引用类型**：

- `L类名;`：对象类型（`Ljava/lang/String;`）
- `[类型`：数组类型（`[I` = int[]，`[[Ljava/lang/String;` = String[][]）

**方法描述符**：

```
(参数类型...)返回类型
```

**示例**：

```java
void method()                    // ()V
int method(String s)             // (Ljava/lang/String;)I
String[] method(int[] arr)       // ([I)[Ljava/lang/String;
void method(int a, String b)     // (ILjava/lang/String;)V
```

---

## 5. 属性表（Attributes）

### 常见属性

**Code 属性**：

存储方法的字节码指令：

```
Code_attribute {
    u2 max_stack;           // 操作数栈最大深度
    u2 max_locals;          // 局部变量表大小
    u4 code_length;         // 字节码长度
    u1 code[code_length];   // 字节码指令
    u2 exception_table_length;
    exception_table[...];   // 异常表
    u2 attributes_count;
    attribute_info attributes[...];
}
```

**LineNumberTable 属性**：

映射字节码偏移量到源码行号：

```
LineNumberTable:
  line 5: 0     // 字节码偏移 0 对应源码第 5 行
  line 6: 8
  line 7: 15
```

**LocalVariableTable 属性**：

存储局部变量信息：

```
LocalVariableTable:
  Start  Length  Slot  Name   Signature
      0      10     0  this   LDemo;
      0      10     1     a   I
      0      10     2     b   I
```

**Signature 属性**：

存储泛型签名：

```java
List<String> list;
```

```
Signature: Ljava/util/List<Ljava/lang/String;>;
```

**Exceptions 属性**：

声明方法可能抛出的异常：

```java
void method() throws IOException, SQLException
```

```
Exceptions:
  throws java.io.IOException, java.sql.SQLException
```

---

## 易错点与边界行为

### 1. 常量池索引陷阱

**long 和 double 占用两个索引**：

```
#5 = Long 100L
#6 = (占位符)
#7 = Utf8 "next"
```

索引 #6 不可用。

### 2. 操作数栈深度计算

**源码**：

```java
int c = a + b * 2;
```

**字节码**：

```
iload_1    // 栈深度：1
iload_2    // 栈深度：2
iconst_2   // 栈深度：3
imul       // 栈深度：2（弹出 2 个，压入 1 个）
iadd       // 栈深度：1
istore_3   // 栈深度：0
```

**max_stack = 3**

### 3. 类型描述符的歧义

**错误**：

```
Ljava.lang.String;  // 错误，使用 . 而非 /
```

**正确**：

```
Ljava/lang/String;
```

### 4. 方法签名的匹配

**源码**：

```java
void method(int[] arr) { }
void method(int[][] arr) { }
```

**字节码签名**：

```
([I)V    // int[]
([[I)V   // int[][]
```

两个方法签名不同，可以重载。

---

## 实际推导案例

### 案例：字符串拼接的字节码

**源码**：

```java
String s = "Hello" + " " + "World";
```

**编译期常量折叠**：

```
ldc "Hello World"  // 直接加载合并后的常量
```

**变量拼接**：

```java
String s = str1 + " " + str2;
```

**字节码**（Java 8）：

```
new StringBuilder
dup
invokespecial StringBuilder.<init>
aload_1              // str1
invokevirtual StringBuilder.append(String)
ldc " "
invokevirtual StringBuilder.append(String)
aload_2              // str2
invokevirtual StringBuilder.append(String)
invokevirtual StringBuilder.toString
astore_3
```

**Java 9+**：

```
aload_1
aload_2
invokedynamic makeConcatWithConstants  // 动态优化
astore_3
```

### 案例：自增运算的字节码

**源码**：

```java
int i = 0;
i++;
```

**字节码**：

```
iconst_0   // 加载常量 0
istore_1   // 存入局部变量 1
iinc 1, 1  // 局部变量 1 自增 1
```

**i++ 与 ++i 的区别**：

```java
int a = i++;  // a = i; i = i + 1;
int b = ++i;  // i = i + 1; b = i;
```

**i++ 的字节码**：

```
iload_1    // 加载 i
iinc 1, 1  // i 自增
istore_2   // 存储原值到 a
```

**++i 的字节码**：

```
iinc 1, 1  // i 自增
iload_1    // 加载新值
istore_2   // 存储到 b
```

---

## 关键点总结

1. **class 文件结构**：魔数 + 版本 + 常量池 + 类信息 + 字段 + 方法 + 属性
2. **常量池**：存储字面量和符号引用，索引从 1 开始
3. **字节码指令**：基于栈，操作数隐式在栈顶
4. **类型描述符**：`I` = int，`Ljava/lang/String;` = String，`[I` = int[]
5. **方法描述符**：`(参数类型...)返回类型`
6. **属性表**：Code、LineNumberTable、Signature 等元数据

---

## 深入一点

### 使用 javap 分析字节码

**基本用法**：

```bash
javap -c Demo.class           # 查看字节码
javap -v Demo.class           # 详细信息（含常量池）
javap -p Demo.class           # 显示私有成员
javap -s Demo.class           # 显示方法签名
```

**输出示例**：

```
Compiled from "Demo.java"
public class Demo
  minor version: 0
  major version: 52
  flags: ACC_PUBLIC, ACC_SUPER
Constant pool:
   #1 = Methodref          #4.#13
   ...
{
  public Demo();
    descriptor: ()V
    flags: ACC_PUBLIC
    Code:
      stack=1, locals=1, args_size=1
         0: aload_0
         1: invokespecial #1
         4: return
}
```

### 字节码验证器

**作用**：确保字节码符合 JVM 规范

**验证阶段**：

1. **文件格式验证**：魔数、版本号、常量池
2. **元数据验证**：语义分析（继承关系、final 类不能被继承）
3. **字节码验证**：数据流分析（栈深度、类型匹配）
4. **符号引用验证**：解析阶段验证引用的类、字段、方法存在

### ASM 库操作字节码

**读取字节码**：

```java
ClassReader cr = new ClassReader("Demo");
ClassVisitor cv = new ClassVisitor(ASM9) {
    @Override
    public MethodVisitor visitMethod(int access, String name, String desc, String signature, String[] exceptions) {
        System.out.println("Method: " + name + desc);
        return super.visitMethod(access, name, desc, signature, exceptions);
    }
};
cr.accept(cv, 0);
```

**生成字节码**：

```java
ClassWriter cw = new ClassWriter(0);
cw.visit(V1_8, ACC_PUBLIC, "GeneratedClass", null, "java/lang/Object", null);
// 添加方法、字段...
byte[] code = cw.toByteArray();
```

---

## 参考资料

- 《深入理解 Java 虚拟机（第3版）》- 第6章 class 文件结构
- 《Java 虚拟机规范（Java SE 8）》- 第4章 class 文件格式
- Oracle 官方文档：[The class File Format](https://docs.oracle.com/javase/specs/jvms/se8/html/jvms-4.html)
- ASM 官方文档：[ASM User Guide](https://asm.ow2.io/asm4-guide.pdf)
- 工具：javap、JClassLib Bytecode Viewer
